pandas_utils/__init__.py
pandas_utils/__main__.py
pandas_utils/__version__.py
pandas_utils/utils.py
python_aux-0.2.0.dist-info/LICENSE
python_aux-0.2.0.dist-info/METADATA
python_aux-0.2.0.dist-info/WHEEL
python_aux-0.2.0.dist-info/top_level.txt
python_aux-0.2.0.dist-info/RECORD
