Metadata-Version: 2.1
Name: python-aux
Version: 0.2.0
Summary: Python Utilities ft. pandas, matplotlib and more
Home-page: https://github.com/kanodiaayush/python-utilities
Author: kanodiaayush, kasince2k
Author-email: kanodiaayush@gmail.com, kasince2k@gmail.com
License: UNKNOWN
Platform: UNKNOWN
Requires-Dist: numpy
Requires-Dist: pandas
Requires-Dist: matplotlib
